agent_skills_cli/__init__.py
agent_skills_cli/cli.py
agent_skills_cli/config.py
agent_skills_cli/errors.py
agent_skills_cli/schema.py
agent_skills_cli/sync.py
agent_skills_cli-0.1.1.dist-info/WHEEL
agent_skills_cli-0.1.1.dist-info/entry_points.txt
agent_skills_cli-0.1.1.dist-info/METADATA
agent_skills_cli-0.1.1.dist-info/RECORD
