Metadata-Version: 2.3
Name: agent-skills-cli
Version: 0.1.1
Summary: A lightweight CLI to install, pin, and enable agent skills across projects with a single local store and per‑agent symlinks.
Requires-Dist: pyyaml>=6.0.3
Requires-Dist: typer>=0.21.0
Requires-Python: >=3.10
